mcsc/__init__.py
mcsc/__main__.py
mcsc/main.py
mcsc/tasks.py
mcsc/telemetry.py
mcsc/update.py
mcsc/utils.py
mcsc/config/settings.py
mcsc/config/update_files.py
mcsc/localization/it.py
mcsc/modules/classes.py
mcsc/modules/logger.py
mcsc/modules/pages.py
mcsc/modules/translations.py
mcsc/modules/user_settings.py
mcsc/modules/utils.py
mcsc/modules/servers/forge.py
mcsc/modules/servers/java.py
mcsc/modules/servers/models.py
mcsc/modules/servers/paper.py
mcsc/modules/servers/utils.py
mcsc/static/logo.png
mcsc/static/style.css
minecraft_server_creator-2.1.0.dist-info/licenses/LICENSE
minecraft_server_creator-2.1.0.dist-info/METADATA
minecraft_server_creator-2.1.0.dist-info/WHEEL
minecraft_server_creator-2.1.0.dist-info/entry_points.txt
minecraft_server_creator-2.1.0.dist-info/top_level.txt
minecraft_server_creator-2.1.0.dist-info/RECORD
