Metadata-Version: 2.4
Name: minecraft-server-creator
Version: 2.1.0
Summary: Minecraft Server Creator - Manage Minecraft servers
Author-email: ddavidel <ddavidel@proton.me>
License: This project is licensed under the Creative Commons Attribution-NonCommercial-ShareAlike 4.0 International License. 
Requires-Python: >=3.12
License-File: LICENSE
Requires-Dist: nicegui
Requires-Dist: requests
Requires-Dist: appdirs
Requires-Dist: pywebview
Requires-Dist: psutil
Requires-Dist: numpy
Dynamic: license-file
